exacttarget/__init__.py
exacttarget/constants.py
exacttarget/exceptions.py
exacttarget/messages.py
exacttarget/settings.py
exacttarget/token.py
django_exact_target-1.1.0.dist-info/LICENSE
django_exact_target-1.1.0.dist-info/METADATA
django_exact_target-1.1.0.dist-info/WHEEL
django_exact_target-1.1.0.dist-info/top_level.txt
django_exact_target-1.1.0.dist-info/RECORD
