Metadata-Version: 2.1
Name: django-exact-target
Version: 1.1.0
Summary: Integration between django and the SalesForce ExactTarget REST API
Home-page: https://gitlab.com/thelabnyc/django-exact-target
Author: Craig Weber
Author-email: crgwbr@gmail.com
License: ISC
Platform: UNKNOWN
Classifier: Development Status :: 5 - Production/Stable
Classifier: Environment :: Web Environment
Classifier: Framework :: Django
Classifier: Intended Audience :: Developers
Classifier: License :: OSI Approved :: ISC License (ISCL)
Classifier: Programming Language :: Python
Classifier: Programming Language :: Python :: 3
License-File: LICENSE
Requires-Dist: Django (>=2.2)
Requires-Dist: sentry-sdk (>=0.5.5)
Requires-Dist: requests (>=2.9.1)
Requires-Dist: simplejson (>=3.8.2)
Provides-Extra: development
Requires-Dist: flake8 (>=3.2.1) ; extra == 'development'
Requires-Dist: requests-mock (>=0.7.0) ; extra == 'development'
Requires-Dist: mock (>=2.0.0) ; extra == 'development'
